setup.py
django_tz/__init__.py
django_tz/fields.py
django_tz/forms.py
django_tz/global_tz.py
django_tz/middleware.py
django_tz/models.py
django_tz/tests.py
django_tz/urls.py
django_tz/utils.py
django_tz/views.py
django_tz/zones.py
django_tz/templatetags/__init__.py
django_tz/templatetags/django_tz_tags.py
django_tz_unknown.egg-info/PKG-INFO
django_tz_unknown.egg-info/SOURCES.txt
django_tz_unknown.egg-info/dependency_links.txt
django_tz_unknown.egg-info/requires.txt
django_tz_unknown.egg-info/top_level.txt
django_tz_unknown.egg-info/zip-safe