Metadata-Version: 1.1
Name: django-tz-unknown
Version: 0.5.dev1
Summary: Django timezones localization app based on global cache (similar to django.utils.translation)
Home-page: UNKNOWN
Author: Rybarczyk Tomasz
Author-email: paluho@gmail.com
License: UNKNOWN
Platform: UNKNOWN
Classifier: Development Status :: 3 - Alpha
Classifier: Environment :: Web Environment
Classifier: Intended Audience :: Developers
Classifier: Operating System :: OS Independent
Classifier: Programming Language :: Python
Classifier: Framework :: Django
